smodex/__init__.py
smodex/downloader.py
smodex/sm_anomaly.py
smodex/sm_climatology.py
smodex/sm_stac.py
smodex/version.py
smodex/visual_sma_ts.py
smodex-1.0.1b0.dist-info/LICENSE
smodex-1.0.1b0.dist-info/METADATA
smodex-1.0.1b0.dist-info/WHEEL
smodex-1.0.1b0.dist-info/entry_points.txt
smodex-1.0.1b0.dist-info/top_level.txt
smodex-1.0.1b0.dist-info/RECORD
